baron_sakender/__init__.py
baron_sakender/cli.py
baron_sakender/core/__init__.py
baron_sakender/core/integrator.py
baron_sakender/core/metrics.py
baron_sakender/core/mhd_system.py
baron_sakender/io/__init__.py
baron_sakender/io/config_manager.py
baron_sakender/io/data_handler.py
baron_sakender/utils/__init__.py
baron_sakender/utils/logger.py
baron_sakender/utils/timer.py
baron_sakender/visualization/__init__.py
baron_sakender/visualization/animator.py
baron_sakender-0.0.1.dist-info/licenses/LICENSE
baron_sakender-0.0.1.dist-info/METADATA
baron_sakender-0.0.1.dist-info/WHEEL
baron_sakender-0.0.1.dist-info/entry_points.txt
baron_sakender-0.0.1.dist-info/top_level.txt
baron_sakender-0.0.1.dist-info/RECORD
