Metadata-Version: 2.4
Name: baron-sakender
Version: 0.0.1
Summary: 2D Ideal MHD Simulator using HLL Riemann Solver with Dedner Divergence Cleaning
Author-email: Sandy Hardian Susanto Herho <sandy.herho@email.ucr.edu>
License: MIT
Project-URL: Homepage, https://github.com/sandyherho/baron-sakender
Keywords: MHD,magnetohydrodynamics,plasma physics,computational physics,fluid dynamics,simulation
Classifier: Development Status :: 4 - Beta
Classifier: Intended Audience :: Science/Research
Classifier: License :: OSI Approved :: MIT License
Classifier: Operating System :: OS Independent
Classifier: Programming Language :: Python :: 3
Classifier: Programming Language :: Python :: 3.9
Classifier: Programming Language :: Python :: 3.10
Classifier: Programming Language :: Python :: 3.11
Classifier: Programming Language :: Python :: 3.12
Classifier: Topic :: Scientific/Engineering :: Physics
Classifier: Topic :: Scientific/Engineering :: Astronomy
Requires-Python: >=3.9
License-File: LICENSE
Requires-Dist: numpy<2.0,>=1.20
Requires-Dist: scipy>=1.7
Requires-Dist: matplotlib>=3.4
Requires-Dist: pandas>=1.3
Requires-Dist: tqdm>=4.60
Requires-Dist: jax>=0.4
Requires-Dist: jaxlib>=0.4
Provides-Extra: gpu
Requires-Dist: jax[cuda12]>=0.4; extra == "gpu"
Provides-Extra: netcdf
Requires-Dist: netCDF4>=1.5; extra == "netcdf"
Provides-Extra: dev
Requires-Dist: pytest>=7.0; extra == "dev"
Requires-Dist: pytest-cov>=4.0; extra == "dev"
Requires-Dist: black>=23.0; extra == "dev"
Requires-Dist: isort>=5.12; extra == "dev"
Requires-Dist: flake8>=6.0; extra == "dev"
Requires-Dist: mypy>=1.0; extra == "dev"
Provides-Extra: docs
Requires-Dist: sphinx>=6.0; extra == "docs"
Requires-Dist: sphinx-rtd-theme>=1.2; extra == "docs"
Requires-Dist: myst-parser>=1.0; extra == "docs"
Dynamic: license-file
